ezoognn/__init__.py
ezoognn/ezoo_graph.py
ezoognn/ezoocall.cpp
ezoognn/ezoocall.cpython-38-darwin.so
ezoognn/libgnn.dylib
ezoognn/libgraph.dylib
ezoognn/libloader.py
ezoognn/rpc_client.py
ezoognn/distribution/__init__.py
ezoognn/distribution/dist_ezoo_replace.py
ezoognn/loader/__init__.py
ezoognn/loader/dataprefetcher.py
ezoognn/loader/loadbatchgraph.py
ezoognn/loader/loadwholegraph.py
ezoognn/loader/dataset/LastFM4KGcn_ezoo_data_graph.py
ezoognn/loader/dataset/__init__.py
ezoognn/loader/dataset/citation_ezoo_data_graph.py
ezoognn/loader/dataset/csv_ezoo_data_graph.py
ezoognn/loader/dataset/ezoo_data_graph.py
ezoognn/loader/dataset/gas_ezoo_data_graph.py
ezoognn/loader/dataset/gowalla_ezoo_data_graph.py
ezoognn/loader/dataset/ieee_fraud_detection_ezoo_data_graph.py
ezoognn/loader/dataset/knowledge_ezoo_data_graph.py
ezoognn/loader/dataset/ml1m_ezoo_data_graph.py
ezoognn/loader/dataset/nowplaying_rs_ezoo_data_graph.py
ezoognn/loader/dataset/ogb_ezoo_data_graph.py
ezoognn/loader/dataset/rdf_ezoo_data_graph.py
ezoognn/loader/dataset/reddit_ezoo_data_graph.py
ezoognn/loader/dataset/jinja_py/heterogeneous_graph_import.jinja-py
ezoognn/loader/dataset/jinja_py/heterogeneous_graph_schema.jinja-py
ezoognn/loader/dataset/jinja_py/homogeneous_graph_import.jinja-py
ezoognn/loader/dataset/jinja_py/homogeneous_graph_schema.jinja-py
ezoognn/nni/__init__.py
ezoognn/nni/nni_params_handler.py
ezoognn/nni/nni_sqlite_handler.py
ezoognn/sampler/__init__.py
ezoognn/sampler/neighbor_sampler.py
ezoognn/sampler/sampling.py
ezoognn/utils/__init__.py
ezoognn/utils/data_utils.py
ezoognn/utils/feature_custom.py
ezoognn/utils/feature_maker.py
ezoognn/utils/feature_transform.py
ezoognn/utils/graph_store.py
ezoognn/utils/graph_utils.py
ezoognn/utils/model_loader.py
ezoognn/utils/painter.py
ezoognn/utils/properties_utils.py
ezoognn/utils/selection_function.py
ezoognn/utils/str_utils.py
ezoognn/utils/text_dispose.py
ezoognnexample/__init__.py
ezoognnexample/distribution/__init__.py
ezoognn-2.0.1.dist-info/METADATA
ezoognn-2.0.1.dist-info/WHEEL
ezoognn-2.0.1.dist-info/top_level.txt
ezoognn-2.0.1.dist-info/RECORD
